channel_box/__init__.py
channel_box/src.py
channel_box/utils.py
channel_box-1.2.0.dist-info/licenses/LICENSE
channel_box-1.2.0.dist-info/METADATA
channel_box-1.2.0.dist-info/WHEEL
channel_box-1.2.0.dist-info/top_level.txt
channel_box-1.2.0.dist-info/RECORD
