Metadata-Version: 2.4
Name: channel-box
Version: 1.2.0
Summary: ChannelBox is a package for FastAPI & Starlette that allows you to make named websocket channels.
Home-page: https://github.com/Sobolev5/channel-box
Author: Sobolev Andrey
Author-email: Sobolev Andrey <email.asobolev@gmail.com>
License: MIT
Project-URL: Homepage, https://github.com/Sobolev5/channel-box
Requires-Python: >=3.11
License-File: LICENSE
Requires-Dist: starlette>=0.37.2
Requires-Dist: websockets>=12.0
Provides-Extra: dev
Requires-Dist: pytest>=8.2; extra == "dev"
Requires-Dist: pytest-asyncio>=0.21; extra == "dev"
Requires-Dist: ruff>=0.4; extra == "dev"
Requires-Dist: uvicorn>=0.30; extra == "dev"
Dynamic: author
Dynamic: home-page
Dynamic: license-file
Dynamic: requires-python
